{
  "fullName": "IOSet.Decimation",
  "enhancements": [
    {
      "description": {
        "short": "Enhances Accuracy and Damage",
        "long": "Enhances the damage of a power by {Boost.Attrib.Damage.Scale}% and accuracy by {Boost.Attrib.Accuracy.Scale}%."
      },
      "isUnique": false,
      "type": "set",
      "effects": [
        {
          "effectType": "Damage",
          "values": [
            {
              "mag": {
                "pve": 0.265
              },
              "probability": 1,
              "duration": 10.25,
              "effectType": "DamageBuff",
              "toWho": "Self",
              "powerFullName": "Boosts.Attuned_Decimation_A.Attuned_Decimation_A",
              "damageType": "Smashing"
            }
          ]
        },
        {
          "effectType": "Boosts_33",
          "values": [
            {
              "mag": {
                "pve": 0.265
              },
              "probability": 1,
              "duration": 10.25,
              "effectType": "DamageBuff",
              "toWho": "Self",
              "powerFullName": "Boosts.Attuned_Decimation_A.Attuned_Decimation_A",
              "damageType": "Lethal"
            },
            {
              "mag": {
                "pve": 0.265
              },
              "probability": 1,
              "duration": 10.25,
              "effectType": "DamageBuff",
              "toWho": "Self",
              "powerFullName": "Boosts.Attuned_Decimation_A.Attuned_Decimation_A",
              "damageType": "Fire"
            },
            {
              "mag": {
                "pve": 0.265
              },
              "probability": 1,
              "duration": 10.25,
              "effectType": "DamageBuff",
              "toWho": "Self",
              "powerFullName": "Boosts.Attuned_Decimation_A.Attuned_Decimation_A",
              "damageType": "Cold"
            },
            {
              "mag": {
                "pve": 0.265
              },
              "probability": 1,
              "duration": 10.25,
              "effectType": "DamageBuff",
              "toWho": "Self",
              "powerFullName": "Boosts.Attuned_Decimation_A.Attuned_Decimation_A",
              "damageType": "Energy"
            },
            {
              "mag": {
                "pve": 0.265
              },
              "probability": 1,
              "duration": 10.25,
              "effectType": "DamageBuff",
              "toWho": "Self",
              "powerFullName": "Boosts.Attuned_Decimation_A.Attuned_Decimation_A",
              "damageType": "Negative"
            },
            {
              "mag": {
                "pve": 0.265
              },
              "probability": 1,
              "duration": 10.25,
              "effectType": "DamageBuff",
              "toWho": "Self",
              "powerFullName": "Boosts.Attuned_Decimation_A.Attuned_Decimation_A",
              "damageType": "Toxic"
            },
            {
              "mag": {
                "pve": 0.265
              },
              "probability": 1,
              "duration": 10.25,
              "effectType": "DamageBuff",
              "toWho": "Self",
              "powerFullName": "Boosts.Attuned_Decimation_A.Attuned_Decimation_A",
              "damageType": "Psionic"
            }
          ]
        },
        {
          "effectType": "Accuracy",
          "values": [
            {
              "mag": {
                "pve": 0.265
              },
              "probability": 1,
              "duration": 10.25,
              "effectType": "Enhancement",
              "eTModifies": 1,
              "toWho": "Self",
              "powerFullName": "Boosts.Attuned_Decimation_A.Attuned_Decimation_A"
            }
          ]
        }
      ],
      "fullName": "Boosts.Attuned_Decimation_A.Attuned_Decimation_A",
      "setName": "Decimation",
      "displayName": "Accuracy/Damage"
    },
    {
      "description": {
        "short": "Enhances Damage and Reduces Endurance Cost",
        "long": "Enhances the damage of a power by {Boost.Attrib.Damage.Scale}% and reduces endurance cost by {Boost.Attrib.Endurance.Scale}%"
      },
      "isUnique": false,
      "type": "set",
      "effects": [
        {
          "effectType": "Damage",
          "values": [
            {
              "mag": {
                "pve": 0.265
              },
              "probability": 1,
              "duration": 10.25,
              "effectType": "DamageBuff",
              "toWho": "Self",
              "powerFullName": "Boosts.Attuned_Decimation_B.Attuned_Decimation_B",
              "damageType": "Smashing"
            }
          ]
        },
        {
          "effectType": "Boosts_33",
          "values": [
            {
              "mag": {
                "pve": 0.265
              },
              "probability": 1,
              "duration": 10.25,
              "effectType": "DamageBuff",
              "toWho": "Self",
              "powerFullName": "Boosts.Attuned_Decimation_B.Attuned_Decimation_B",
              "damageType": "Lethal"
            },
            {
              "mag": {
                "pve": 0.265
              },
              "probability": 1,
              "duration": 10.25,
              "effectType": "DamageBuff",
              "toWho": "Self",
              "powerFullName": "Boosts.Attuned_Decimation_B.Attuned_Decimation_B",
              "damageType": "Fire"
            },
            {
              "mag": {
                "pve": 0.265
              },
              "probability": 1,
              "duration": 10.25,
              "effectType": "DamageBuff",
              "toWho": "Self",
              "powerFullName": "Boosts.Attuned_Decimation_B.Attuned_Decimation_B",
              "damageType": "Cold"
            },
            {
              "mag": {
                "pve": 0.265
              },
              "probability": 1,
              "duration": 10.25,
              "effectType": "DamageBuff",
              "toWho": "Self",
              "powerFullName": "Boosts.Attuned_Decimation_B.Attuned_Decimation_B",
              "damageType": "Energy"
            },
            {
              "mag": {
                "pve": 0.265
              },
              "probability": 1,
              "duration": 10.25,
              "effectType": "DamageBuff",
              "toWho": "Self",
              "powerFullName": "Boosts.Attuned_Decimation_B.Attuned_Decimation_B",
              "damageType": "Negative"
            },
            {
              "mag": {
                "pve": 0.265
              },
              "probability": 1,
              "duration": 10.25,
              "effectType": "DamageBuff",
              "toWho": "Self",
              "powerFullName": "Boosts.Attuned_Decimation_B.Attuned_Decimation_B",
              "damageType": "Toxic"
            },
            {
              "mag": {
                "pve": 0.265
              },
              "probability": 1,
              "duration": 10.25,
              "effectType": "DamageBuff",
              "toWho": "Self",
              "powerFullName": "Boosts.Attuned_Decimation_B.Attuned_Decimation_B",
              "damageType": "Psionic"
            }
          ]
        },
        {
          "effectType": "Endurance",
          "values": [
            {
              "mag": {
                "pve": 0.265
              },
              "probability": 1,
              "duration": 10.25,
              "effectType": "Enhancement",
              "eTModifies": 8,
              "toWho": "Self",
              "powerFullName": "Boosts.Attuned_Decimation_B.Attuned_Decimation_B"
            }
          ]
        }
      ],
      "fullName": "Boosts.Attuned_Decimation_B.Attuned_Decimation_B",
      "setName": "Decimation",
      "displayName": "Damage/Endurance"
    },
    {
      "description": {
        "short": "Enhances Damage and Recharge",
        "long": "Enhances the damage of a power by {Boost.Attrib.Damage.Scale}% and reduces recharge time by {Boost.Attrib.Recharge.Scale}%"
      },
      "isUnique": false,
      "type": "set",
      "effects": [
        {
          "effectType": "Damage",
          "values": [
            {
              "mag": {
                "pve": 0.265
              },
              "probability": 1,
              "duration": 10.25,
              "effectType": "DamageBuff",
              "toWho": "Self",
              "powerFullName": "Boosts.Attuned_Decimation_C.Attuned_Decimation_C",
              "damageType": "Smashing"
            }
          ]
        },
        {
          "effectType": "Boosts_33",
          "values": [
            {
              "mag": {
                "pve": 0.265
              },
              "probability": 1,
              "duration": 10.25,
              "effectType": "DamageBuff",
              "toWho": "Self",
              "powerFullName": "Boosts.Attuned_Decimation_C.Attuned_Decimation_C",
              "damageType": "Lethal"
            },
            {
              "mag": {
                "pve": 0.265
              },
              "probability": 1,
              "duration": 10.25,
              "effectType": "DamageBuff",
              "toWho": "Self",
              "powerFullName": "Boosts.Attuned_Decimation_C.Attuned_Decimation_C",
              "damageType": "Fire"
            },
            {
              "mag": {
                "pve": 0.265
              },
              "probability": 1,
              "duration": 10.25,
              "effectType": "DamageBuff",
              "toWho": "Self",
              "powerFullName": "Boosts.Attuned_Decimation_C.Attuned_Decimation_C",
              "damageType": "Cold"
            },
            {
              "mag": {
                "pve": 0.265
              },
              "probability": 1,
              "duration": 10.25,
              "effectType": "DamageBuff",
              "toWho": "Self",
              "powerFullName": "Boosts.Attuned_Decimation_C.Attuned_Decimation_C",
              "damageType": "Energy"
            },
            {
              "mag": {
                "pve": 0.265
              },
              "probability": 1,
              "duration": 10.25,
              "effectType": "DamageBuff",
              "toWho": "Self",
              "powerFullName": "Boosts.Attuned_Decimation_C.Attuned_Decimation_C",
              "damageType": "Negative"
            },
            {
              "mag": {
                "pve": 0.265
              },
              "probability": 1,
              "duration": 10.25,
              "effectType": "DamageBuff",
              "toWho": "Self",
              "powerFullName": "Boosts.Attuned_Decimation_C.Attuned_Decimation_C",
              "damageType": "Toxic"
            },
            {
              "mag": {
                "pve": 0.265
              },
              "probability": 1,
              "duration": 10.25,
              "effectType": "DamageBuff",
              "toWho": "Self",
              "powerFullName": "Boosts.Attuned_Decimation_C.Attuned_Decimation_C",
              "damageType": "Psionic"
            }
          ]
        },
        {
          "effectType": "Recharge",
          "values": [
            {
              "mag": {
                "pve": 0.265
              },
              "probability": 1,
              "duration": 10.25,
              "effectType": "Enhancement",
              "eTModifies": 25,
              "toWho": "Self",
              "powerFullName": "Boosts.Attuned_Decimation_C.Attuned_Decimation_C"
            }
          ]
        }
      ],
      "fullName": "Boosts.Attuned_Decimation_C.Attuned_Decimation_C",
      "setName": "Decimation",
      "displayName": "Damage/Recharge"
    },
    {
      "description": {
        "short": "Enhances Accuracy, Reduces Endurance Cost and Increases Attack Rate",
        "long": "Enhances the accuracy of a power by {Boost.Attrib.Accuracy.Scale}%, reduces recharge time by {Boost.Attrib.Recharge.Scale}% and endurance cost by {Boost.Attrib.Endurance.Scale}%."
      },
      "isUnique": false,
      "type": "set",
      "effects": [
        {
          "effectType": "Accuracy",
          "values": [
            {
              "mag": {
                "pve": 0.212
              },
              "probability": 1,
              "duration": 10.25,
              "effectType": "Enhancement",
              "eTModifies": 1,
              "toWho": "Self",
              "powerFullName": "Boosts.Attuned_Decimation_D.Attuned_Decimation_D"
            }
          ]
        },
        {
          "effectType": "Endurance",
          "values": [
            {
              "mag": {
                "pve": 0.212
              },
              "probability": 1,
              "duration": 10.25,
              "effectType": "Enhancement",
              "eTModifies": 8,
              "toWho": "Self",
              "powerFullName": "Boosts.Attuned_Decimation_D.Attuned_Decimation_D"
            }
          ]
        },
        {
          "effectType": "Recharge",
          "values": [
            {
              "mag": {
                "pve": 0.212
              },
              "probability": 1,
              "duration": 10.25,
              "effectType": "Enhancement",
              "eTModifies": 25,
              "toWho": "Self",
              "powerFullName": "Boosts.Attuned_Decimation_D.Attuned_Decimation_D"
            }
          ]
        }
      ],
      "fullName": "Boosts.Attuned_Decimation_D.Attuned_Decimation_D",
      "setName": "Decimation",
      "displayName": "Accuracy/Endurance/Recharge"
    },
    {
      "description": {
        "short": "Enhances Damage, Reduces Endurance Cost and Increases Attack Rate",
        "long": "Enhances the accuracy of a power by {Boost.Attrib.Accuracy.Scale}% and damage by {Boost.Attrib.Damage.Scale}% and reduces recharge time by {Boost.Attrib.Recharge.Scale}%."
      },
      "isUnique": false,
      "type": "set",
      "effects": [
        {
          "effectType": "Damage",
          "values": [
            {
              "mag": {
                "pve": 0.212
              },
              "probability": 1,
              "duration": 10.25,
              "effectType": "DamageBuff",
              "toWho": "Self",
              "powerFullName": "Boosts.Attuned_Decimation_E.Attuned_Decimation_E",
              "damageType": "Smashing"
            }
          ]
        },
        {
          "effectType": "Boosts_33",
          "values": [
            {
              "mag": {
                "pve": 0.212
              },
              "probability": 1,
              "duration": 10.25,
              "effectType": "DamageBuff",
              "toWho": "Self",
              "powerFullName": "Boosts.Attuned_Decimation_E.Attuned_Decimation_E",
              "damageType": "Lethal"
            },
            {
              "mag": {
                "pve": 0.212
              },
              "probability": 1,
              "duration": 10.25,
              "effectType": "DamageBuff",
              "toWho": "Self",
              "powerFullName": "Boosts.Attuned_Decimation_E.Attuned_Decimation_E",
              "damageType": "Fire"
            },
            {
              "mag": {
                "pve": 0.212
              },
              "probability": 1,
              "duration": 10.25,
              "effectType": "DamageBuff",
              "toWho": "Self",
              "powerFullName": "Boosts.Attuned_Decimation_E.Attuned_Decimation_E",
              "damageType": "Cold"
            },
            {
              "mag": {
                "pve": 0.212
              },
              "probability": 1,
              "duration": 10.25,
              "effectType": "DamageBuff",
              "toWho": "Self",
              "powerFullName": "Boosts.Attuned_Decimation_E.Attuned_Decimation_E",
              "damageType": "Energy"
            },
            {
              "mag": {
                "pve": 0.212
              },
              "probability": 1,
              "duration": 10.25,
              "effectType": "DamageBuff",
              "toWho": "Self",
              "powerFullName": "Boosts.Attuned_Decimation_E.Attuned_Decimation_E",
              "damageType": "Negative"
            },
            {
              "mag": {
                "pve": 0.212
              },
              "probability": 1,
              "duration": 10.25,
              "effectType": "DamageBuff",
              "toWho": "Self",
              "powerFullName": "Boosts.Attuned_Decimation_E.Attuned_Decimation_E",
              "damageType": "Toxic"
            },
            {
              "mag": {
                "pve": 0.212
              },
              "probability": 1,
              "duration": 10.25,
              "effectType": "DamageBuff",
              "toWho": "Self",
              "powerFullName": "Boosts.Attuned_Decimation_E.Attuned_Decimation_E",
              "damageType": "Psionic"
            }
          ]
        },
        {
          "effectType": "Accuracy",
          "values": [
            {
              "mag": {
                "pve": 0.212
              },
              "probability": 1,
              "duration": 10.25,
              "effectType": "Enhancement",
              "eTModifies": 1,
              "toWho": "Self",
              "powerFullName": "Boosts.Attuned_Decimation_E.Attuned_Decimation_E"
            }
          ]
        },
        {
          "effectType": "Recharge",
          "values": [
            {
              "mag": {
                "pve": 0.212
              },
              "probability": 1,
              "duration": 10.25,
              "effectType": "Enhancement",
              "eTModifies": 25,
              "toWho": "Self",
              "powerFullName": "Boosts.Attuned_Decimation_E.Attuned_Decimation_E"
            }
          ]
        }
      ],
      "fullName": "Boosts.Attuned_Decimation_E.Attuned_Decimation_E",
      "setName": "Decimation",
      "displayName": "Accuracy/Damage/Recharge"
    },
    {
      "description": {
        "short": "Chance for Buildup",
        "long": "UNIQUE -- No more than 1 enhancement of this type may be slotted by a character.  Gives a chance to have a \"\"Build Up\"\" power effect the caster.  This effect will trigger roughly 1 time per minute."
      },
      "isUnique": true,
      "type": "set",
      "effects": [
        {
          "effectType": "Boost",
          "values": [
            {
              "mag": {
                "pve": 1
              },
              "procsPerMinute": 1,
              "cancelOnMiss": true,
              "duration": 10,
              "effectType": "GrantPower",
              "ticks": 1,
              "toWho": "Self",
              "powerFullName": "Boosts.Attuned_Decimation_F.Attuned_Decimation_F"
            }
          ]
        }
      ],
      "fullName": "Boosts.Attuned_Decimation_F.Attuned_Decimation_F",
      "setName": "Decimation",
      "displayName": "Chance for Buildup",
      "hasGrantPowerEffect": true
    }
  ],
  "levels": {
    "min": 25,
    "max": 40
  },
  "bonuses": [
    {
      "description": {
        "short": "+Res (Energy, Negative, Mez)",
        "long": "Increases Energy and Negative Energy resistance by 1.5% and Mez Resistance by 2.5%"
      },
      "isUnique": false,
      "isPvP": false,
      "unlocked": 2,
      "powerSetIndex": 56,
      "fullName": "Set_Bonus.Set_Bonus.Energy_Neg_Mez_Res_1",
      "setName": "Set_Bonus",
      "displayName": "Tiny Energy, Negative Energy and Mez Resistance",
      "ignoreStrength": true,
      "effects": [
        {
          "effectType": "Ones",
          "values": [
            {
              "mag": {
                "pve": 0.015
              },
              "probability": 1,
              "duration": 10.25,
              "effectType": "Resistance",
              "toWho": "Self",
              "powerFullName": "Set_Bonus.Set_Bonus.Energy_Neg_Mez_Res_1",
              "damageType": "Energy"
            },
            {
              "mag": {
                "pve": 0.015
              },
              "probability": 1,
              "duration": 10.25,
              "effectType": "Resistance",
              "toWho": "Self",
              "powerFullName": "Set_Bonus.Set_Bonus.Energy_Neg_Mez_Res_1",
              "damageType": "Negative"
            },
            {
              "mag": {
                "pve": 0.025
              },
              "probability": 1,
              "duration": 10.25,
              "effectType": "MezResist",
              "toWho": "Self",
              "powerFullName": "Set_Bonus.Set_Bonus.Energy_Neg_Mez_Res_1",
              "mezType": "Immobilization"
            },
            {
              "mag": {
                "pve": 0.025
              },
              "probability": 1,
              "duration": 10.25,
              "effectType": "MezResist",
              "toWho": "Self",
              "powerFullName": "Set_Bonus.Set_Bonus.Energy_Neg_Mez_Res_1",
              "mezType": "Hold"
            },
            {
              "mag": {
                "pve": 0.025
              },
              "probability": 1,
              "duration": 10.25,
              "effectType": "MezResist",
              "toWho": "Self",
              "powerFullName": "Set_Bonus.Set_Bonus.Energy_Neg_Mez_Res_1",
              "mezType": "Stun"
            },
            {
              "mag": {
                "pve": 0.025
              },
              "probability": 1,
              "duration": 10.25,
              "effectType": "MezResist",
              "toWho": "Self",
              "powerFullName": "Set_Bonus.Set_Bonus.Energy_Neg_Mez_Res_1",
              "mezType": "Sleep"
            },
            {
              "mag": {
                "pve": 0.025
              },
              "probability": 1,
              "duration": 10.25,
              "effectType": "MezResist",
              "toWho": "Self",
              "powerFullName": "Set_Bonus.Set_Bonus.Energy_Neg_Mez_Res_1",
              "mezType": "Terrorize"
            },
            {
              "mag": {
                "pve": 0.025
              },
              "probability": 1,
              "duration": 10.25,
              "effectType": "MezResist",
              "toWho": "Self",
              "powerFullName": "Set_Bonus.Set_Bonus.Energy_Neg_Mez_Res_1",
              "mezType": "Confuse"
            }
          ]
        }
      ]
    },
    {
      "description": {
        "short": "+Max HP",
        "long": "Increases maximum health by 1.13%."
      },
      "isUnique": false,
      "isPvP": false,
      "unlocked": 3,
      "powerSetIndex": 285,
      "fullName": "Set_Bonus.Set_Bonus.Increased_Health_2",
      "setName": "Set_Bonus",
      "displayName": "Small Increased Health Bonus",
      "ignoreStrength": true,
      "effects": [
        {
          "effectType": "HealSelf",
          "values": [
            {
              "mag": {
                "pve": 13.5535383
              },
              "probability": 1,
              "duration": 10.75,
              "effectType": "HitPoints",
              "toWho": "Self",
              "powerFullName": "Set_Bonus.Set_Bonus.Increased_Health_2"
            }
          ]
        }
      ]
    },
    {
      "description": {
        "short": "+Max End",
        "long": "Increases maximum Endurance by 2.25%."
      },
      "isUnique": false,
      "isPvP": false,
      "unlocked": 4,
      "powerSetIndex": 224,
      "fullName": "Set_Bonus.Set_Bonus.Increased_Endurance_4",
      "setName": "Set_Bonus",
      "displayName": "Large Increased Endurance Bonus",
      "ignoreStrength": true,
      "effects": [
        {
          "effectType": "Ones",
          "values": [
            {
              "mag": {
                "pve": 2.25
              },
              "probability": 1,
              "duration": 10.75,
              "effectType": "Endurance",
              "toWho": "Self",
              "powerFullName": "Set_Bonus.Set_Bonus.Increased_Endurance_4"
            }
          ]
        }
      ]
    },
    {
      "description": {
        "short": "+Recharge Time",
        "long": "Improves the Recharge Time of all of your powers by 6.25%."
      },
      "isUnique": false,
      "isPvP": false,
      "unlocked": 5,
      "powerSetIndex": 140,
      "fullName": "Set_Bonus.Set_Bonus.Improved_Recharge_Time_4",
      "setName": "Set_Bonus",
      "displayName": "Large Improved Recharge Time Bonus",
      "ignoreStrength": true,
      "effects": [
        {
          "effectType": "Ones",
          "values": [
            {
              "mag": {
                "pve": 0.0625
              },
              "probability": 1,
              "duration": 10.25,
              "effectType": "Enhancement",
              "eTModifies": 25,
              "toWho": "Self",
              "powerFullName": "Set_Bonus.Set_Bonus.Improved_Recharge_Time_4"
            }
          ]
        }
      ]
    },
    {
      "description": {
        "short": "+Res (Toxic, Psionic, Mez)",
        "long": "Increases Toxic and Psionic resistance by 4.5% and Mez Resistance by 7.5%"
      },
      "isUnique": false,
      "isPvP": false,
      "unlocked": 6,
      "powerSetIndex": 525,
      "fullName": "Set_Bonus.Set_Bonus.Toxic_Psi_Mez_Res_5",
      "setName": "Set_Bonus",
      "displayName": "Huge Toxic, Psionic and Mez Resistance",
      "ignoreStrength": true,
      "effects": [
        {
          "effectType": "Ones",
          "values": [
            {
              "mag": {
                "pve": 0.045
              },
              "probability": 1,
              "duration": 10.25,
              "effectType": "Resistance",
              "toWho": "Self",
              "powerFullName": "Set_Bonus.Set_Bonus.Toxic_Psi_Mez_Res_5",
              "damageType": "Toxic"
            },
            {
              "mag": {
                "pve": 0.045
              },
              "probability": 1,
              "duration": 10.25,
              "effectType": "Resistance",
              "toWho": "Self",
              "powerFullName": "Set_Bonus.Set_Bonus.Toxic_Psi_Mez_Res_5",
              "damageType": "Psionic"
            },
            {
              "mag": {
                "pve": 0.075
              },
              "probability": 1,
              "duration": 10.25,
              "effectType": "MezResist",
              "toWho": "Self",
              "powerFullName": "Set_Bonus.Set_Bonus.Toxic_Psi_Mez_Res_5",
              "mezType": "Immobilization"
            },
            {
              "mag": {
                "pve": 0.075
              },
              "probability": 1,
              "duration": 10.25,
              "effectType": "MezResist",
              "toWho": "Self",
              "powerFullName": "Set_Bonus.Set_Bonus.Toxic_Psi_Mez_Res_5",
              "mezType": "Hold"
            },
            {
              "mag": {
                "pve": 0.075
              },
              "probability": 1,
              "duration": 10.25,
              "effectType": "MezResist",
              "toWho": "Self",
              "powerFullName": "Set_Bonus.Set_Bonus.Toxic_Psi_Mez_Res_5",
              "mezType": "Stun"
            },
            {
              "mag": {
                "pve": 0.075
              },
              "probability": 1,
              "duration": 10.25,
              "effectType": "MezResist",
              "toWho": "Self",
              "powerFullName": "Set_Bonus.Set_Bonus.Toxic_Psi_Mez_Res_5",
              "mezType": "Sleep"
            },
            {
              "mag": {
                "pve": 0.075
              },
              "probability": 1,
              "duration": 10.25,
              "effectType": "MezResist",
              "toWho": "Self",
              "powerFullName": "Set_Bonus.Set_Bonus.Toxic_Psi_Mez_Res_5",
              "mezType": "Terrorize"
            },
            {
              "mag": {
                "pve": 0.075
              },
              "probability": 1,
              "duration": 10.25,
              "effectType": "MezResist",
              "toWho": "Self",
              "powerFullName": "Set_Bonus.Set_Bonus.Toxic_Psi_Mez_Res_5",
              "mezType": "Confuse"
            }
          ]
        }
      ]
    }
  ],
  "setType": 2,
  "displayName": "Decimation",
  "imageName": "sDecimation.png"
}