{
  "fullName": "IOSet.Freebird",
  "enhancements": [
    {
      "description": {
        "short": "-End Cost",
        "long": "Reduces the endurance cost of a power by {Boost.Attrib.Endurance.Scale}%."
      },
      "isUnique": false,
      "type": "set",
      "effects": [
        {
          "effectType": "Endurance",
          "values": [
            {
              "etModifies": "EnduranceDiscount",
              "mag": {
                "pve": 0.424
              },
              "probability": 1,
              "duration": 10.25,
              "effectType": "Enhancement",
              "toWho": "self",
              "powerFullName": "Boosts.Attuned_Freebird_A.Attuned_Freebird_A"
            }
          ]
        }
      ],
      "fullName": "Boosts.Attuned_Freebird_A.Attuned_Freebird_A",
      "setName": "Freebird",
      "displayName": "Endurance"
    },
    {
      "description": {
        "short": "+Fly",
        "long": "Enhances the flight speed of a power by {Boost.Attrib.Fly.Scale}%."
      },
      "isUnique": false,
      "type": "set",
      "effects": [
        {
          "effectType": "Fly",
          "values": [
            {
              "etModifies": "SpeedFlying",
              "mag": {
                "pve": 0.424
              },
              "probability": 1,
              "duration": 10.25,
              "effectType": "Enhancement",
              "toWho": "self",
              "powerFullName": "Boosts.Attuned_Freebird_B.Attuned_Freebird_B"
            }
          ]
        }
      ],
      "fullName": "Boosts.Attuned_Freebird_B.Attuned_Freebird_B",
      "setName": "Freebird",
      "displayName": "Fly"
    },
    {
      "description": {
        "short": "Grants Stealth",
        "long": "UNIQUE -- No more than 1 enhancement of this type may be slotted by a character.  May not be slotted if you have any other enhancements which grant stealth.  Grants Stealth for 120 seconds when used in an instant effect power."
      },
      "isUnique": true,
      "type": "set",
      "effects": [
        {
          "effectType": "Stealth",
          "values": [
            {
              "mag": {
                "pve": 30
              },
              "cancelOnMiss": true,
              "probability": 1,
              "duration": 120,
              "effectType": "StealthRadius",
              "toWho": "self",
              "powerFullName": "Boosts.Attuned_Freebird_C.Attuned_Freebird_C"
            }
          ]
        },
        {
          "effectType": "Ones",
          "values": [
            {
              "mag": {
                "pve": 300
              },
              "cancelOnMiss": true,
              "probability": 1,
              "duration": 120,
              "effectType": "StealthRadiusPlayer",
              "toWho": "self",
              "powerFullName": "Boosts.Attuned_Freebird_C.Attuned_Freebird_C"
            },
            {
              "mag": {
                "pve": 0.8
              },
              "cancelOnMiss": true,
              "probability": 1,
              "duration": 120,
              "effectType": "Translucency",
              "toWho": "self",
              "powerFullName": "Boosts.Attuned_Freebird_C.Attuned_Freebird_C"
            }
          ]
        }
      ],
      "fullName": "Boosts.Attuned_Freebird_C.Attuned_Freebird_C",
      "setName": "Freebird",
      "displayName": "Stealth"
    }
  ],
  "levels": {
    "min": 15,
    "max": 50
  },
  "bonuses": [
    {
      "pve": {
        "self": {
          "Regeneration": {
            "8": {
              "aggregates": [
                true
              ],
              "hasAggregates": false,
              "unlocked": 2,
              "display": "8% Regen"
            }
          }
        }
      },
      "pvp": {}
    },
    {
      "pve": {
        "self": {
          "HitPoints": {
            "1807.14": {
              "aggregates": [
                true
              ],
              "hasAggregates": false,
              "unlocked": 3,
              "display": "1807.14% Max HP"
            }
          }
        }
      },
      "pvp": {}
    }
  ],
  "setType": 17,
  "setTypeName": "Flight",
  "displayName": "Freebird",
  "imageName": "sFreeBird.png"
}