{"fullName":"IOSet.Karma","enhancements":[{"type":"set","description":{"short":"+DEF (all), Reduces End cost","long":"Enhances the defense of a power by {Boost.Attrib.Defense.Scale}% and reduces endurance cost by {Boost.Attrib.Endurance.Scale}%"},"isUnique":false,"fullName":"Boosts.Attuned_Karma_A.Attuned_Karma_A","setName":"Karma","displayName":"Defense/Endurance","effects":[{"mag":0.159375,"effectId":"Defense"},{"mag":0.159375,"effectId":"Boosts_20","damageType":10},{"mag":0.159375,"effectId":"Boosts_20","damageType":11},{"mag":0.159375,"effectId":"Boosts_20","damageType":12},{"mag":0.159375,"effectId":"Boosts_20","damageType":1},{"mag":0.159375,"effectId":"Boosts_20","damageType":2},{"mag":0.159375,"effectId":"Boosts_20","damageType":3},{"mag":0.159375,"effectId":"Boosts_20","damageType":4},{"mag":0.159375,"effectId":"Boosts_20","damageType":5},{"mag":0.159375,"effectId":"Boosts_20","damageType":6},{"mag":0.159375,"effectId":"Boosts_20","damageType":8},{"mag":0.265,"effectId":"Endurance"}]},{"type":"set","description":{"short":"+DEF (all), +Rech","long":"Enhances the defense of a power by {Boost.Attrib.Defense.Scale}% and reduces recharge time by {Boost.Attrib.Recharge.Scale}%"},"isUnique":false,"fullName":"Boosts.Attuned_Karma_B.Attuned_Karma_B","setName":"Karma","displayName":"Defense/Recharge","effects":[{"mag":0.159375,"effectId":"Defense"},{"mag":0.159375,"effectId":"Boosts_20","damageType":10},{"mag":0.159375,"effectId":"Boosts_20","damageType":11},{"mag":0.159375,"effectId":"Boosts_20","damageType":12},{"mag":0.159375,"effectId":"Boosts_20","damageType":1},{"mag":0.159375,"effectId":"Boosts_20","damageType":2},{"mag":0.159375,"effectId":"Boosts_20","damageType":3},{"mag":0.159375,"effectId":"Boosts_20","damageType":4},{"mag":0.159375,"effectId":"Boosts_20","damageType":5},{"mag":0.159375,"effectId":"Boosts_20","damageType":6},{"mag":0.159375,"effectId":"Boosts_20","damageType":8},{"mag":0.265,"effectId":"Recharge"}]},{"type":"set","description":{"short":"-KB","long":"Provides 4 points of Knockback protection."},"isUnique":false,"fullName":"Boosts.Attuned_Karma_C.Attuned_Karma_C","setName":"Karma","displayName":"Knockback Protection","effects":[{"cancelOnMiss":true,"mag":-4,"variableModified":true,"effectId":"Knockback","stacking":1}]}],"levels":{"min":10,"max":30},"bonuses":["Increased_Endurance_2","Increased_Health_3"],"setType":7,"displayName":"Karma","imageName":"sKarma.png"}