{
  "type": "standard",
  "description": "Enhances the damage of a power.",
  "displayName": "Damage",
  "fullName": "Enhancement_Damage",
  "isUnique": false,
  "imageName": "Damage.png",
  "effects": {
    "TO": [
      { "mag": 0.0833, "effectId": "Damage", "damageType": 1 },
      { "mag": 0.0833, "effectId": "Ones", "damageType": 2 },
      { "mag": 0.0833, "effectId": "Ones", "damageType": 3 },
      { "mag": 0.0833, "effectId": "Ones", "damageType": 4 },
      { "mag": 0.0833, "effectId": "Ones", "damageType": 5 },
      { "mag": 0.0833, "effectId": "Ones", "damageType": 6 },
      { "mag": 0.0833, "effectId": "Ones", "damageType": 7 },
      { "mag": 0.0833, "effectId": "Ones", "damageType": 8 }
    ],
    "SO": [
      { "mag": 0.3333, "effectId": "Damage", "damageType": 1 },
      { "mag": 0.3333, "effectId": "Ones", "damageType": 2 },
      { "mag": 0.3333, "effectId": "Ones", "damageType": 3 },
      { "mag": 0.3333, "effectId": "Ones", "damageType": 4 },
      { "mag": 0.3333, "effectId": "Ones", "damageType": 5 },
      { "mag": 0.3333, "effectId": "Ones", "damageType": 6 },
      { "mag": 0.3333, "effectId": "Ones", "damageType": 7 },
      { "mag": 0.3333, "effectId": "Ones", "damageType": 8 }
    ],
    "DO": [
      { "mag": 0.1666, "effectId": "Damage", "damageType": 1 },
      { "mag": 0.1666, "effectId": "Ones", "damageType": 2 },
      { "mag": 0.1666, "effectId": "Ones", "damageType": 3 },
      { "mag": 0.1666, "effectId": "Ones", "damageType": 4 },
      { "mag": 0.1666, "effectId": "Ones", "damageType": 5 },
      { "mag": 0.1666, "effectId": "Ones", "damageType": 6 },
      { "mag": 0.1666, "effectId": "Ones", "damageType": 7 },
      { "mag": 0.1666, "effectId": "Ones", "damageType": 8 }
    ],
    "IO": {
      "10": [
        { "mag": 0.1, "effectId": "Damage", "damageType": 1 },
        { "mag": 0.1, "effectId": "Ones", "damageType": 2 },
        { "mag": 0.1, "effectId": "Ones", "damageType": 3 },
        { "mag": 0.1, "effectId": "Ones", "damageType": 4 },
        { "mag": 0.1, "effectId": "Ones", "damageType": 5 },
        { "mag": 0.1, "effectId": "Ones", "damageType": 6 },
        { "mag": 0.1, "effectId": "Ones", "damageType": 7 },
        { "mag": 0.1, "effectId": "Ones", "damageType": 8 }
      ],
      "15": [
        { "mag": 0.15, "effectId": "Damage", "damageType": 1 },
        { "mag": 0.15, "effectId": "Ones", "damageType": 2 },
        { "mag": 0.15, "effectId": "Ones", "damageType": 3 },
        { "mag": 0.15, "effectId": "Ones", "damageType": 4 },
        { "mag": 0.15, "effectId": "Ones", "damageType": 5 },
        { "mag": 0.15, "effectId": "Ones", "damageType": 6 },
        { "mag": 0.15, "effectId": "Ones", "damageType": 7 },
        { "mag": 0.15, "effectId": "Ones", "damageType": 8 }
      ],
      "20": [
        { "mag": 0.2, "effectId": "Damage", "damageType": 1 },
        { "mag": 0.2, "effectId": "Ones", "damageType": 2 },
        { "mag": 0.2, "effectId": "Ones", "damageType": 3 },
        { "mag": 0.2, "effectId": "Ones", "damageType": 4 },
        { "mag": 0.2, "effectId": "Ones", "damageType": 5 },
        { "mag": 0.2, "effectId": "Ones", "damageType": 6 },
        { "mag": 0.2, "effectId": "Ones", "damageType": 7 },
        { "mag": 0.2, "effectId": "Ones", "damageType": 8 }
      ],
      "25": [
        { "mag": 0.25, "effectId": "Damage", "damageType": 1 },
        { "mag": 0.25, "effectId": "Ones", "damageType": 2 },
        { "mag": 0.25, "effectId": "Ones", "damageType": 3 },
        { "mag": 0.25, "effectId": "Ones", "damageType": 4 },
        { "mag": 0.25, "effectId": "Ones", "damageType": 5 },
        { "mag": 0.25, "effectId": "Ones", "damageType": 6 },
        { "mag": 0.25, "effectId": "Ones", "damageType": 7 },
        { "mag": 0.25, "effectId": "Ones", "damageType": 8 }
      ],
      "30": [
        { "mag": 0.3, "effectId": "Damage", "damageType": 1 },
        { "mag": 0.3, "effectId": "Ones", "damageType": 2 },
        { "mag": 0.3, "effectId": "Ones", "damageType": 3 },
        { "mag": 0.3, "effectId": "Ones", "damageType": 4 },
        { "mag": 0.3, "effectId": "Ones", "damageType": 5 },
        { "mag": 0.3, "effectId": "Ones", "damageType": 6 },
        { "mag": 0.3, "effectId": "Ones", "damageType": 7 },
        { "mag": 0.3, "effectId": "Ones", "damageType": 8 }
      ],
      "35": [
        { "mag": 0.325, "effectId": "Damage", "damageType": 1 },
        { "mag": 0.325, "effectId": "Ones", "damageType": 2 },
        { "mag": 0.325, "effectId": "Ones", "damageType": 3 },
        { "mag": 0.325, "effectId": "Ones", "damageType": 4 },
        { "mag": 0.325, "effectId": "Ones", "damageType": 5 },
        { "mag": 0.325, "effectId": "Ones", "damageType": 6 },
        { "mag": 0.325, "effectId": "Ones", "damageType": 7 },
        { "mag": 0.325, "effectId": "Ones", "damageType": 8 }
      ],
      "40": [
        { "mag": 0.35, "effectId": "Damage", "damageType": 1 },
        { "mag": 0.35, "effectId": "Ones", "damageType": 2 },
        { "mag": 0.35, "effectId": "Ones", "damageType": 3 },
        { "mag": 0.35, "effectId": "Ones", "damageType": 4 },
        { "mag": 0.35, "effectId": "Ones", "damageType": 5 },
        { "mag": 0.35, "effectId": "Ones", "damageType": 6 },
        { "mag": 0.35, "effectId": "Ones", "damageType": 7 },
        { "mag": 0.35, "effectId": "Ones", "damageType": 8 }
      ],
      "45": [
        { "mag": 0.375, "effectId": "Damage", "damageType": 1 },
        { "mag": 0.375, "effectId": "Ones", "damageType": 2 },
        { "mag": 0.375, "effectId": "Ones", "damageType": 3 },
        { "mag": 0.375, "effectId": "Ones", "damageType": 4 },
        { "mag": 0.375, "effectId": "Ones", "damageType": 5 },
        { "mag": 0.375, "effectId": "Ones", "damageType": 6 },
        { "mag": 0.375, "effectId": "Ones", "damageType": 7 },
        { "mag": 0.375, "effectId": "Ones", "damageType": 8 }
      ],
      "50": [
        { "mag": 0.4, "effectId": "Damage", "damageType": 1 },
        { "mag": 0.4, "effectId": "Ones", "damageType": 2 },
        { "mag": 0.4, "effectId": "Ones", "damageType": 3 },
        { "mag": 0.4, "effectId": "Ones", "damageType": 4 },
        { "mag": 0.4, "effectId": "Ones", "damageType": 5 },
        { "mag": 0.4, "effectId": "Ones", "damageType": 6 },
        { "mag": 0.4, "effectId": "Ones", "damageType": 7 },
        { "mag": 0.4, "effectId": "Ones", "damageType": 8 }
      ],
      "cap": [
        { "mag": 0.424, "effectId": "Damage", "damageType": 1 },
        { "mag": 0.424, "effectId": "Boosts_33", "damageType": 2 },
        { "mag": 0.424, "effectId": "Boosts_33", "damageType": 3 },
        { "mag": 0.424, "effectId": "Boosts_33", "damageType": 4 },
        { "mag": 0.424, "effectId": "Boosts_33", "damageType": 5 },
        { "mag": 0.424, "effectId": "Boosts_33", "damageType": 6 },
        { "mag": 0.424, "effectId": "Boosts_33", "damageType": 7 },
        { "mag": 0.424, "effectId": "Boosts_33", "damageType": 8 }
      ]
    }
  }
}
